cfgnet/__init__.py
cfgnet/analyze/__init__.py
cfgnet/analyze/analyzer.py
cfgnet/analyze/csv_writer.py
cfgnet/analyze/timeout.py
cfgnet/config_types/__init__.py
cfgnet/config_types/config_type_inferer.py
cfgnet/config_types/config_types.py
cfgnet/conflicts/__init__.py
cfgnet/conflicts/conflict.py
cfgnet/conflicts/conflict_detector.py
cfgnet/exceptions/__init__.py
cfgnet/exceptions/exceptions.py
cfgnet/exporter/__init__.py
cfgnet/exporter/exporter.py
cfgnet/launcher.py
cfgnet/launcher_configuration.py
cfgnet/linker/__init__.py
cfgnet/linker/equality_linker.py
cfgnet/linker/link.py
cfgnet/linker/linker.py
cfgnet/linker/linker_manager.py
cfgnet/linker/static_blacklist.py
cfgnet/network/__init__.py
cfgnet/network/ignorefile.py
cfgnet/network/network.py
cfgnet/network/network_configuration.py
cfgnet/network/nodes.py
cfgnet/plugins/__init__.py
cfgnet/plugins/concept/__init__.py
cfgnet/plugins/concept/alluxio_plugin.py
cfgnet/plugins/concept/android_plugin.py
cfgnet/plugins/concept/angular_plugin.py
cfgnet/plugins/concept/ansible_playbook_plugin.py
cfgnet/plugins/concept/ansible_plugin.py
cfgnet/plugins/concept/apache_webserver_plugin.py
cfgnet/plugins/concept/cargo_plugin.py
cfgnet/plugins/concept/circleci_plugin.py
cfgnet/plugins/concept/cypress_plugin.py
cfgnet/plugins/concept/django_plugin.py
cfgnet/plugins/concept/docker_compose_plugin.py
cfgnet/plugins/concept/docker_plugin.py
cfgnet/plugins/concept/elastisearch_plugin.py
cfgnet/plugins/concept/flutter_plugin.py
cfgnet/plugins/concept/github_actions_plugin.py
cfgnet/plugins/concept/gradle_plugin.py
cfgnet/plugins/concept/hadoop_common_plugin.py
cfgnet/plugins/concept/hadoop_hbase_plugin.py
cfgnet/plugins/concept/hadoop_hdfs_plugin.py
cfgnet/plugins/concept/kafka_plugin.py
cfgnet/plugins/concept/mapreduce_plugin.py
cfgnet/plugins/concept/maven_plugin.py
cfgnet/plugins/concept/mongodb_plugin.py
cfgnet/plugins/concept/mysql_plugin.py
cfgnet/plugins/concept/nodejs_plugin.py
cfgnet/plugins/concept/php_plugin.py
cfgnet-1.0.5.dist-info/COPYING
cfgnet-1.0.5.dist-info/METADATA
cfgnet-1.0.5.dist-info/WHEEL
cfgnet-1.0.5.dist-info/entry_points.txt
cfgnet-1.0.5.dist-info/RECORD
