Metadata-Version: 2.3
Name: CfgNet
Version: 1.0.5
Summary: A Framework for Tracking Configuration Dependencies Across a Software Project
License: GPL-3.0+
Keywords: configuration
Author: Sebastian Simon
Author-email: ssimon@informatik.uni-leipzig.de
Maintainer: Sebastian Simon
Maintainer-email: ssimon@informatik.uni-leipzig.de
Requires-Python: >=3.11,<3.13
Classifier: License :: OSI Approved :: GNU General Public License v3 or later (GPLv3+)
Classifier: Programming Language :: Python :: 3
Classifier: Programming Language :: Python :: 3.11
Classifier: Programming Language :: Python :: 3.12
Requires-Dist: GitPython (>=3.1.24,<4.0.0)
Requires-Dist: PyYAML (>=6.0,<7.0)
Requires-Dist: Sphinx (>=5.0.2,<6.0.0)
Requires-Dist: apacheconfig (>=0.3.2,<0.4.0)
Requires-Dist: click (>=8.0.3,<9.0.0)
Requires-Dist: dockerfile (>=3.2.0,<4.0.0)
Requires-Dist: flatdict (>=4.0.1,<5.0.0)
Requires-Dist: graphviz (>=0.17,<0.18)
Requires-Dist: lxml (>=4.6.3,<5.0.0)
Requires-Dist: mypy (==1.2)
Requires-Dist: sphinxcontrib-spelling (>=7.3.2,<8.0.0)
Requires-Dist: types-PyYAML (>=6.0.1,<7.0.0)
Requires-Dist: types-toml (>=0.10.1,<0.11.0)
Project-URL: Homepage, https://github.com/digital-bauhaus/CfgNet
